imephu/__init__.py
imephu/cli.py
imephu/finder_chart.py
imephu/geometry.py
imephu/py.typed
imephu/schema.json
imephu/utils.py
imephu/annotation/__init__.py
imephu/annotation/motion.py
imephu/annotation/general/__init__.py
imephu/annotation/general/arrow.py
imephu/annotation/general/circle.py
imephu/annotation/general/crosshairs.py
imephu/annotation/general/empty.py
imephu/annotation/general/group.py
imephu/annotation/general/line_path.py
imephu/annotation/general/rectangle.py
imephu/annotation/general/text.py
imephu/salt/finder_chart.py
imephu/salt/utils.py
imephu/salt/annotation/__init__.py
imephu/salt/annotation/nir.py
imephu/salt/annotation/rss.py
imephu/salt/annotation/salticam.py
imephu/salt/annotation/telescope.py
imephu/service/horizons.py
imephu/service/survey.py
imephutest-0.1.0.dist-info/LICENSE
imephutest-0.1.0.dist-info/METADATA
imephutest-0.1.0.dist-info/WHEEL
imephutest-0.1.0.dist-info/entry_points.txt
imephutest-0.1.0.dist-info/top_level.txt
imephutest-0.1.0.dist-info/RECORD
