Metadata-Version: 2.1
Name: imephutest
Version: 0.1.0
Summary: Generate finder charts for the Southern African Large Telescope (SALT).
Home-page: https://github.com/saltastroops/saao-pypackage-cookiecutter
Author: Southern African Large Telescope (SALT)
Author-email: salthelp@salt.ac.za
License: MIT
Classifier: License :: OSI Approved :: MIT License
License-File: LICENSE
Requires-Dist: astropy (>=5.0)
Requires-Dist: astroquery (>=0.4.5)
Requires-Dist: jsonschema (>=4.4.0)
Requires-Dist: python-dateutil (>=2.8.2)
Requires-Dist: defusedxml (>=0.7.1)
Requires-Dist: matplotlib (!=3.4.0,>=3.1)
Requires-Dist: pikepdf (>=4.4.1)
Requires-Dist: pyyaml (>=6.0)
Requires-Dist: requests (>=2.27.1)
Requires-Dist: typer[all] (>=0.4.0)
